MANIFEST.in
README.rst
setup.cfg
setup.py
/root/cykdtree/cykdtree/cykdtree/c_parallel_kdtree.cpp
/root/cykdtree/cykdtree/cykdtree/c_utils.cpp
cgal4py/__init__.py
cgal4py/parallel.py
cgal4py/plot.py
cgal4py/run_parallel_delaunay.py
cgal4py/run_test.py
cgal4py.egg-info/PKG-INFO
cgal4py.egg-info/SOURCES.txt
cgal4py.egg-info/dependency_links.txt
cgal4py.egg-info/not-zip-safe
cgal4py.egg-info/top_level.txt
cgal4py/delaunay/__init__.py
cgal4py/delaunay/c_delaunay2.cpp
cgal4py/delaunay/c_delaunay2.hpp
cgal4py/delaunay/c_delaunay3.cpp
cgal4py/delaunay/c_delaunay3.hpp
cgal4py/delaunay/c_delaunayD.hpp
cgal4py/delaunay/c_parallel_delaunayD.cpp
cgal4py/delaunay/c_parallel_delaunayD.hpp
cgal4py/delaunay/c_periodic_delaunay2.cpp
cgal4py/delaunay/c_periodic_delaunay2.hpp
cgal4py/delaunay/c_periodic_delaunay3.cpp
cgal4py/delaunay/c_periodic_delaunay3.hpp
cgal4py/delaunay/c_tools.hpp
cgal4py/delaunay/delaunay2.cpp
cgal4py/delaunay/delaunay2.pxd
cgal4py/delaunay/delaunay2.pyx
cgal4py/delaunay/delaunay3.cpp
cgal4py/delaunay/delaunay3.pxd
cgal4py/delaunay/delaunay3.pyx
cgal4py/delaunay/delaunayD.pxd
cgal4py/delaunay/delaunayD.pyx
cgal4py/delaunay/parallel_delaunayD.cpp
cgal4py/delaunay/parallel_delaunayD.pxd
cgal4py/delaunay/parallel_delaunayD.pyx
cgal4py/delaunay/periodic_delaunay2.cpp
cgal4py/delaunay/periodic_delaunay2.pxd
cgal4py/delaunay/periodic_delaunay2.pyx
cgal4py/delaunay/periodic_delaunay3.cpp
cgal4py/delaunay/periodic_delaunay3.pxd
cgal4py/delaunay/periodic_delaunay3.pyx
cgal4py/delaunay/tools.cpp
cgal4py/delaunay/tools.pxd
cgal4py/delaunay/tools.pyx
cgal4py/domain_decomp/__init__.py
cgal4py/tests/__init__.py
cgal4py/tests/scaling.py
cgal4py/tests/test_cgal4py.py
cgal4py/tests/test_delaunay.py
cgal4py/tests/test_delaunay2.py
cgal4py/tests/test_delaunay3.py
cgal4py/tests/test_delaunayD.py
cgal4py/tests/test_domain_decomp.py
cgal4py/tests/test_parallel.py
cgal4py/tests/test_periodic_delaunay2.py
cgal4py/tests/test_periodic_delaunay3.py
cgal4py/tests/test_plot.py