Metadata-Version: 1.1
Name: cgal4py
Version: 0.2.0
Summary: Python interface for CGAL Triangulations
Home-page: https://langmm@bitbucket.org/langmm/cgal4py
Author: Meagan Lang
Author-email: langmm.astro@gmail.com
License: BSD
Keywords: delaunay,voronoi,cgal,triangulation,tessellation
Platform: UNKNOWN
Classifier: Programming Language :: Python
Classifier: Programming Language :: C++
Classifier: Operating System :: OS Independent
Classifier: Intended Audience :: Science/Research
Classifier: License :: OSI Approved :: BSD License
Classifier: Natural Language :: English
Classifier: Topic :: Scientific/Engineering
Classifier: Topic :: Scientific/Engineering :: Astronomy
Classifier: Topic :: Scientific/Engineering :: Mathematics
Classifier: Topic :: Scientific/Engineering :: Physics
Classifier: Development Status :: 3 - Alpha
